README.md
setup.py
xspike/__init__.py
xspike/cmd_utils.py
xspike/comet_client.py
xspike/gpu_queuer.py
xspike/io.py
xspike/prompts.py
xspike/redis_client.py
xspike/redis_maintainer.py
xspike/run_exp_plan.py
xspike/utils.py
xspike/visualizer.py
xspike.egg-info/PKG-INFO
xspike.egg-info/SOURCES.txt
xspike.egg-info/dependency_links.txt
xspike.egg-info/entry_points.txt
xspike.egg-info/requires.txt
xspike.egg-info/top_level.txt