Metadata-Version: 2.1
Name: xspike
Version: 0.3.10
Summary: 工具包，包含 Redis 安装、基于 Redis 的GPU 任务队列管理等功能
Home-page: https://github.com/deng1fan
Author: deng1fan
Author-email: dengyifan@iie.ac.cn
Keywords: gpu,queuer,redis
Requires-Python: >=3.7
